taskmanager/__init__.py
taskmanager/admin.py
taskmanager/apps.py
taskmanager/compat.py
taskmanager/logging.py
taskmanager/models.py
taskmanager/notifications.py
taskmanager/settings.py
taskmanager/tasks.py
taskmanager/urls.py
taskmanager/utils.py
taskmanager/uwsgidecorators_wrapper.py
taskmanager/views.py
taskmanager/management/__init__.py
taskmanager/management/base.py
taskmanager/management/commands/__init__.py
taskmanager/management/commands/collectcommands.py
taskmanager/management/commands/restart_despooled_tasks.py
taskmanager/management/commands/test_command.py
taskmanager/management/commands/test_livelogging_command.py
taskmanager/management/commands/test_logging_command.py
taskmanager/migrations/0001_initial.py
taskmanager/migrations/0002_auto_20201001_1751.py
taskmanager/migrations/__init__.py
taskmanager/static/img/iconfinder_ic_wrap_text.png
taskmanager/static/img/icons8-double-down-32.png
taskmanager/static/img/icons8-new-document-32.png
taskmanager/static/js/axios.js
taskmanager/static/js/linkify.min.js
taskmanager/static/js/menu_filter_collapse.js
taskmanager/static/js/vue.js
taskmanager/templates/live_log_viewer.html
taskmanager/templates/log_viewer.html
taskmanager/templates/admin/appcommand_changeform.html
taskmanager/templates/admin/custom_changeform.html
taskmanager/templates/admin/edit_inline/tabular_reports.html
django_uwsgi_taskmanager-2.3.5.dist-info/LICENSE.md
django_uwsgi_taskmanager-2.3.5.dist-info/METADATA
django_uwsgi_taskmanager-2.3.5.dist-info/WHEEL
django_uwsgi_taskmanager-2.3.5.dist-info/top_level.txt
django_uwsgi_taskmanager-2.3.5.dist-info/RECORD
