Metadata-Version: 2.1
Name: django-uwsgi-taskmanager
Version: 2.3.5
Summary: Django application to manage async tasks via admin interface, using uWSGI spooler.
Home-page: https://github.com/openpolis/django-uwsgi-taskmanager.git
Author: Gabriele Giaccari, Gabriele Lucci, Guglielmo Celata, Paolo Melchiorre
Author-email: lab@openpolis.it
License: AGPLv3 License
Project-URL: Bug Reports, https://github.com/openpolis/django-uwsgi-taskmanager/issues
Project-URL: Source Code, https://github.com/openpolis/django-uwsgi-taskmanager
Keywords: async,cron,django,manager,spooler,task,timer,uwsgi
Classifier: Development Status :: 4 - Beta
Classifier: Environment :: Web Environment
Classifier: Framework :: Django :: 1.11
Classifier: Framework :: Django :: 2.0
Classifier: Framework :: Django :: 2.1
Classifier: Framework :: Django :: 2.2
Classifier: Framework :: Django :: 3.0
Classifier: Framework :: Django
Classifier: Intended Audience :: Developers
Classifier: License :: OSI Approved :: GNU Affero General Public License v3
Classifier: Operating System :: OS Independent
Classifier: Programming Language :: Python :: 3 :: Only
Classifier: Programming Language :: Python :: 3.6
Classifier: Programming Language :: Python :: 3.7
Classifier: Programming Language :: Python
Classifier: Topic :: Internet :: WWW/HTTP :: Dynamic Content
Classifier: Topic :: Internet :: WWW/HTTP
Requires-Python: ~=3.6
License-File: LICENSE.md
Requires-Dist: django (>=1.11)
Requires-Dist: uwsgi
Requires-Dist: file-read-backwards (>=2.0.0)
Provides-Extra: dev
Requires-Dist: black ; extra == 'dev'
Requires-Dist: bump2version ; extra == 'dev'
Requires-Dist: flake8-bugbear ; extra == 'dev'
Requires-Dist: flake8-docstrings ; extra == 'dev'
Requires-Dist: flake8-isort ; extra == 'dev'
Requires-Dist: flake8 ; extra == 'dev'
Requires-Dist: isort ; extra == 'dev'
Requires-Dist: mypy ; extra == 'dev'
Requires-Dist: pytz ; extra == 'dev'
Requires-Dist: pre-commit ; extra == 'dev'
Provides-Extra: docs
Requires-Dist: sphinx ; extra == 'docs'
Requires-Dist: sphinx-django-command ; extra == 'docs'
Requires-Dist: sphinx-rtd-theme ; extra == 'docs'
Requires-Dist: sphinx-autobuild ; extra == 'docs'
Requires-Dist: pyembed-rst ; extra == 'docs'
Provides-Extra: notifications
Requires-Dist: slack-sdk ; extra == 'notifications'
